cmprs_core/__init__.py
cmprs_core/clipping.py
cmprs_core/common.py
cmprs_core/config.py
cmprs_core/kashin.py
cmprs_core/random_utils.py
cmprs_core/reshape.py
cmprs_core/rounding.py
cmprs_core/scale.py
cmprs_core/sparsification.py
cmprs_core/split.py
cmprs_core/transform.py
cmprs_core/bitrate/__init__.py
cmprs_core/bitrate/huffman_coding.py
cmprs_core/bitrate/optimal.py
cmprs_core/bitrate/recursive_elias_coding.py
cmprs_eden/__init__.py
cmprs_eden/drive.py
cmprs_eden/linear.py
cmprs_eden-0.1a3.dist-info/LICENSE
cmprs_eden-0.1a3.dist-info/METADATA
cmprs_eden-0.1a3.dist-info/WHEEL
cmprs_eden-0.1a3.dist-info/top_level.txt
cmprs_eden-0.1a3.dist-info/RECORD
