Metadata-Version: 2.1
Name: cmprs-eden
Version: 0.1a3
Summary: EDEN compression written in PyTorch
Home-page: https://github.com/cmprs/eden
Author: Amit Portnoy
Author-email: amit.portnoy@gmail.com
Project-URL: Bug Tracker, https://github.com/cmprs/eden/issues
Classifier: Programming Language :: Python :: 3
Classifier: License :: OSI Approved :: MIT License
Classifier: Operating System :: OS Independent
Requires-Python: >=3.9
License-File: LICENSE
Requires-Dist: numpy (==1.*)
Requires-Dist: mpmath (==1.2.*)
Requires-Dist: torch (>=1.10)
Requires-Dist: hadamard-transform (==0.1.*)
Provides-Extra: preprocess
Requires-Dist: sympy (==1.10.*) ; extra == 'preprocess'
Requires-Dist: tqdm (==4.*) ; extra == 'preprocess'
Provides-Extra: test
Requires-Dist: pytest ; extra == 'test'
